LICENSE.txt
MANIFEST.in
README.md
setup.py
abuseipdb/__init__.py
abuseipdb/_app.py
abuseipdb/parameters.py
abuseipdb.egg-info/PKG-INFO
abuseipdb.egg-info/SOURCES.txt
abuseipdb.egg-info/dependency_links.txt
abuseipdb.egg-info/entry_points.txt
abuseipdb.egg-info/requires.txt
abuseipdb.egg-info/top_level.txt