Metadata-Version: 2.1
Name: abuseipdb
Version: 1.1.0
Summary: AbuseIPDb wrapper for IP checking and trouble reporting
Home-page: https://github.com/vsecades/AbuseIpDb
Author: Valentin Secades M.
Author-email: vsecades@qxdev.com
License: UNKNOWN
Project-URL: Funding, https://www.paypal.me/VSecades/5
Project-URL: Bug Reports, https://github.com/vsecades/AbuseIpDb/issues
Project-URL: Source, https://github.com/vsecades/AbuseIpDb/
Keywords: abuseipdb,blacklisting,ip reporting
Platform: UNKNOWN
Classifier: Development Status :: 4 - Beta
Classifier: Intended Audience :: Developers
Classifier: Topic :: Software Development :: Build Tools
Classifier: License :: OSI Approved :: MIT License
Classifier: Programming Language :: Python :: 2
Classifier: Programming Language :: Python :: 2.7
Provides-Extra: test
Provides-Extra: dev
